in_toolset/__init__.py
in_toolset/common.py
in_toolset/config.py
in_toolset/main.py
in_toolset/data/config.txt
in_toolset/data/style.json
in_toolset/data/tools.json
in_toolset/model/__init__.py
in_toolset/model/base.py
in_toolset/model/pnml.py
in_toolset/model/project.py
in_toolset/model/ui.py
in_toolset/ui/__init__.py
in_toolset/ui/app.py
in_toolset/ui/common.py
in_toolset/ui/enterprise.py
in_toolset/ui/industry.py
in_toolset/ui/menu.py
in_toolset/ui/scene.py
in_toolset/ui/settings.py
in_toolset/ui/tools.py
in_toolset/ui/view.py
in_toolset/ui/window.py
in_toolset-0.1.3.dist-info/LICENCE
in_toolset-0.1.3.dist-info/METADATA
in_toolset-0.1.3.dist-info/WHEEL
in_toolset-0.1.3.dist-info/entry_points.txt
in_toolset-0.1.3.dist-info/top_level.txt
in_toolset-0.1.3.dist-info/RECORD
