Metadata-Version: 2.1
Name: in-toolset
Version: 0.1.3
Summary: An editor and simulator for industry workflow nets (inets), a model of interorganisational workflows based on petrinets
Home-page: https://github.com/jakobwuhrer/in-toolset
Author: Example Author
Author-email: author@example.com
License: UNKNOWN
Platform: UNKNOWN
Classifier: Programming Language :: Python :: 3
Classifier: License :: OSI Approved :: GNU General Public License (GPL)
Classifier: Operating System :: OS Independent
Requires-Python: >=3.6
Requires-Dist: pyqt5
